restless_dungeon/__init__.py
restless_dungeon/game.py
restless_dungeon/main.py
restless_dungeon/scripts/__init__.py
restless_dungeon/scripts/player.py
restless_dungeon/scripts/rooms/__init__.py
restless_dungeon/scripts/rooms/empty_room.py
restless_dungeon/scripts/rooms/explosives_room.py
restless_dungeon/scripts/rooms/rest_room.py
restless_dungeon/scripts/rooms/skeleton_room.py
restless_dungeon/scripts/rooms/stair_room.py
restless_dungeon/scripts/rooms/stranger_room.py
restless_dungeon/scripts/rooms/walls_closing_room.py
restless_dungeon/scripts/rooms/zombie_room.py
restless_dungeon-1.0.9.dist-info/METADATA
restless_dungeon-1.0.9.dist-info/WHEEL
restless_dungeon-1.0.9.dist-info/entry_points.txt
restless_dungeon-1.0.9.dist-info/licenses/LICENSE
restless_dungeon-1.0.9.dist-info/RECORD
