Metadata-Version: 2.4
Name: restless-dungeon
Version: 1.0.9
Summary: A text-based dungeon adventure game.
Project-URL: Repository, https://github.com/Dekoder-py/restless_dungeon
Author-email: Dekoder-py <dekod3r.py@gmail.com>
License-Expression: MIT
License-File: LICENSE
Keywords: adventure,cli,dungeon,game,interactive
Requires-Python: >=3.7
Requires-Dist: rich
